{
	"name": "Leela_GenericSQL_LinkedServices",
	"type": "Microsoft.DataFactory/factories/linkedservices",
	"properties": {
		"description": "Leela_GenericSQL_LinkedServices",
		"parameters": {
			"ServerName": {
				"type": "string"
			},
			"DBName": {
				"type": "string"
			},
			"Username": {
				"type": "string"
			},
			"Password": {
				"type": "string"
			}
		},
		"annotations": [],
		"type": "AzureSqlDatabase",
		"typeProperties": {
			"connectionString": "Integrated Security=False;Encrypt=True;Connection Timeout=30;Data Source=@{linkedService().ServerName};Initial Catalog=@{linkedService().DBName};User ID=@{linkedService().Username};Password=@{linkedService().Password}"
		}
	}
}